lch_scrapy/__init__.py
lch_scrapy/downhtml.py
lch_scrapy/multipage.py
lch_scrapy-1.0.0.dist-info/METADATA
lch_scrapy-1.0.0.dist-info/WHEEL
lch_scrapy-1.0.0.dist-info/top_level.txt
lch_scrapy-1.0.0.dist-info/RECORD
